mia_simexp/__init__.py
mia_simexp/anemoi_client.py
mia_simexp/anemoi_messages.py
mia_simexp/archiver.py
mia_simexp/collaborator_config.py
mia_simexp/continuations.py
mia_simexp/github_issue.py
mia_simexp/imp_clip.py
mia_simexp/playwright_writer.py
mia_simexp/processor.py
mia_simexp/session_file_handler.py
mia_simexp/session_manager.py
mia_simexp/session_sharing.py
mia_simexp/simex.py
mia_simexp/simfetcher.py
mia_simexp/timestamp_utils.py
mia_simexp/utils/__init__.py
mia_simexp-0.6.0.dist-info/METADATA
mia_simexp-0.6.0.dist-info/WHEEL
mia_simexp-0.6.0.dist-info/entry_points.txt
mia_simexp-0.6.0.dist-info/top_level.txt
mia_simexp-0.6.0.dist-info/RECORD
