Metadata-Version: 2.4
Name: mia-simexp
Version: 0.6.0
Summary: Mia's fork of SimExp - Terminal-to-AI communication with A2A session management
Home-page: https://github.com/gerico1007/simexp
Author: gerico1007
Author-email: Mia Isabelle <mia@example.com>, gerico1007 <gerico@jgwill.com>
Project-URL: Homepage, https://github.com/miadisabelle/simexp
Project-URL: Documentation, https://github.com/miadisabelle/simexp#readme
Project-URL: Repository, https://github.com/miadisabelle/simexp.git
Project-URL: Issues, https://github.com/miadisabelle/simexp/issues
Keywords: simplenote,ai,terminal,a2a,session,mcp,browser-automation
Classifier: Programming Language :: Python :: 3
Classifier: Programming Language :: Python :: 3.10
Classifier: Programming Language :: Python :: 3.11
Classifier: Programming Language :: Python :: 3.12
Classifier: License :: OSI Approved :: MIT License
Classifier: Operating System :: OS Independent
Classifier: Development Status :: 4 - Beta
Classifier: Intended Audience :: Developers
Classifier: Topic :: Internet :: WWW/HTTP
Classifier: Topic :: Utilities
Requires-Python: >=3.6
Requires-Dist: requests
Requires-Dist: beautifulsoup4
Requires-Dist: pyperclip
Requires-Dist: pyyaml
Requires-Dist: fetcher
Requires-Dist: playwright>=1.40.0
Requires-Dist: tlid>=0.1.0
Requires-Dist: mia-anemoi>=0.1.0
Provides-Extra: dev
Requires-Dist: pytest>=7.0; extra == "dev"
Requires-Dist: pytest-asyncio>=0.21.0; extra == "dev"
Requires-Dist: pytest-cov>=4.0; extra == "dev"
Requires-Dist: black>=23.0; extra == "dev"
Requires-Dist: ruff>=0.1.0; extra == "dev"
Requires-Dist: build>=1.0; extra == "dev"
Requires-Dist: twine>=4.0; extra == "dev"
Provides-Extra: mcp
Requires-Dist: mcp>=1.0.0; extra == "mcp"
Provides-Extra: anemoi
Requires-Dist: mia-anemoi[mcp]>=0.1.0; extra == "anemoi"
Provides-Extra: all
Requires-Dist: mia-simexp[anemoi,dev,mcp]; extra == "all"
Dynamic: author
Dynamic: home-page
Dynamic: requires-python
